LICENSE
src/rx/__init__.py
src/rx/compression_data/__init__.py
src/rx/compression_data/example_1MP.png
src/rx/rx.py
src/rx/utils.py
rx_algorithm-1.0.0.dist-info/LICENSE
rx_algorithm-1.0.0.dist-info/METADATA
rx_algorithm-1.0.0.dist-info/WHEEL
rx_algorithm-1.0.0.dist-info/entry_points.txt
rx_algorithm-1.0.0.dist-info/RECORD
